politeness/__init__.py
politeness/classifier.py
politeness/constants.py
politeness/corenlp-url.txt
politeness/helpers.py
politeness/strategies.py
politeness/vectorizer.py
politeness/data/__init__.py
politeness/data/download.py
politeness/data/stack-exchange.parsed.json
politeness/data/wikipedia.parsed.json
politeness/features/bigram-feats.p
politeness/features/liu-negative-words.txt
politeness/features/liu-positive-words.txt
politeness/features/unigram-feats.p
politeness/models/politeness-svm.p
politeness-0.1.2.dist-info/DESCRIPTION.rst
politeness-0.1.2.dist-info/METADATA
politeness-0.1.2.dist-info/RECORD
politeness-0.1.2.dist-info/WHEEL
politeness-0.1.2.dist-info/metadata.json
politeness-0.1.2.dist-info/top_level.txt
